JdatEditor/JdatEditor.py
JdatEditor/__init__.py
jdateditor-0.1.1.dist-info/licenses/License
jdateditor-0.1.1.dist-info/METADATA
jdateditor-0.1.1.dist-info/WHEEL
jdateditor-0.1.1.dist-info/top_level.txt
jdateditor-0.1.1.dist-info/RECORD
