Metadata-Version: 2.4
Name: JdatEditor
Version: 0.1.1
Summary: Module minimaliste pour lire et éditer des fichiers JDAT
Author-email: GabiMinecraft02 <gabriel.m020913@gmail.com>
License: MIT
Keywords: JDAT,editor,data
Classifier: Programming Language :: Python :: 3
Classifier: License :: OSI Approved :: MIT License
Classifier: Operating System :: OS Independent
Requires-Python: >=3.8
License-File: License
Dynamic: license-file
